text2keyword.py
keyword_module-1.1.0.dist-info/METADATA
keyword_module-1.1.0.dist-info/WHEEL
keyword_module-1.1.0.dist-info/top_level.txt
keyword_module-1.1.0.dist-info/RECORD
